{
	"devices": [
		{
			"id": 3,
			"title": "Button",
			"registers": [
				{
					"name": "Button Status",
					"type": "r",
					"reg": 27,
					"bytes": 1,
					"si": ""
				}
			]
		},
		{
			"id": 4,
			"title": "Color Sensor",
			"registers": [
				{
					"name": "Darkness",
					"type": "r",
					"reg": 32,
					"bytes": 2,
					"si": ""
				}
			]
		},
		{
			"id": 9,
			"title": "LED",
			"registers": [
				{
					"name": "Led Brightness",
					"type": "w",
					"reg": 26,
					"bytes": 1,
					"si": "",
					"min": 0,
					"max": 255,
					"subtype": "range"
				}
			]
		},
		{
			"id": 10,
			"title": "Line Sensor",
			"registers": [
				{
					"name": "Line Status",
					"type": "r",
					"reg": 27,
					"bytes": 1,
					"si": ""
				}
			]
		},
		{
			"id": 18,
			"title": "Sound Sensor",
			"registers": [
				{
					"name": "Sound Value",
					"type": "r",
					"reg": 26,
					"bytes": 1,
					"si": ""
				},
				{
					"name": "Clap Count",
					"type": "r",
					"reg": 27,
					"bytes": 1,
					"si": ""
				},
				{
					"name": "Last Sound Time",
					"type": "r",
					"reg": 28,
					"bytes": 2,
					"si": ""
				}
			]
		},
		{
			"id": 19,
			"title": "Potentiometer",
			"registers": [
				{
					"name": "Potentiometer Value",
					"type": "r",
					"reg": 26,
					"bytes": 2,
					"si": ""
				}
			]
		},
		{
			"id": 20,
			"title": "Atm. Pressure",
			"registers": [
				{
					"name": "Pressure",
					"type": "r",
					"reg": 24,
					"bytes": 4,
					"si": "mmHg"
				},
				{
					"name": "Altitude",
					"type": "r",
					"reg": 28,
					"bytes": 4,
					"si": "m"
				},
				{
					"name": "Temperature",
					"type": "r",
					"reg": 36,
					"bytes": 2,
					"si": "C"
				}
			]
		},
		{
			"id": 21,
			"title": "RGB LED",
			"registers": [
				{
					"name": "Red",
					"type": "w",
					"reg": 27,
					"bytes": 1,
					"si": "",
					"min": 0,
					"max": 255,
					"subtype": "range"
				},
				{
					"name": "Green",
					"type": "w",
					"reg": 26,
					"bytes": 1,
					"si": "",
					"min": 0,
					"max": 255,
					"subtype": "range"
				},
				{
					"name": "Blue",
					"type": "w",
					"reg": 28,
					"bytes": 1,
					"si": "",
					"min": 0,
					"max": 255,
					"subtype": "range"
				}
			]
		},
		{
			"id": 22,
			"title": "Temperature/Humidity",
			"registers": [
				{
					"name": "Humidity",
					"type": "r",
					"reg": 24,
					"bytes": 2,
					"si": ""
				},
				{
					"name": "Temperature",
					"type": "r",
					"reg": 28,
					"bytes": 2,
					"si": ""
				}
			]
		},
		{
			"id": 23,
			"title": "Limit Sensor",
			"registers": [
				{
					"name": "Limit Status",
					"type": "r",
					"reg": 27,
					"bytes": 1,
					"si": ""
				}
			]
		},
		{
			"id": 24,
			"title": "Sound Emmiter",
			"registers": [
				{
					"name": "Frequency",
					"type": "w",
					"reg": 26,
					"bytes": 2,
					"si": "Hz",
					"min": 0,
					"max": 5000,
					"subtype": "range"
				},
				{
					"name": "Porosity",
					"type": "w",
					"reg": 28,
					"bytes": 2,
					"si": "%",
					"min": 0,
					"max": 255,
					"subtype": "range"
				}
			]
		},
		{
			"id": 25,
			"title": "Light Sensor",
			"registers": [
				{
					"name": "Brightness",
					"type": "r",
					"reg": 26,
					"bytes": 2,
					"si": ""
				}
			]
		}
	]
}
